[1,0,0,[["cc.Mesh",["_native","_hash","_struct"],1,11]],[[0,0,1,2,3]],[[0,".bin",3363008351,[{"primitives":[{"primitiveMode":7,"vertexBundelIndices":[0],"indexView":{"offset":5436,"length":1344,"count":336,"stride":4}}],"vertexBundles":[{"view":{"offset":0,"length":5436,"count":151,"stride":36},"attributes":[{"name":"a_position","format":32,"isNormalized":false},{"name":"a_normal","format":32,"isNormalized":false},{"name":"a_color","format":32,"isNormalized":false}]}]},"minPosition",8,[1,-0.15000000596046448,2.6587300300598145,-0.8442500233650208],"maxPosition",8,[1,0.15000000596046448,3.2639899253845215,-0.24523000419139862]]],-1],0,0,[],[],[]]
