[1,0,0,[["cc.Mesh",["_native","_hash","_struct"],1,11]],[[0,0,1,2,3]],[[0,".bin",1112881793,[{"primitives":[{"primitiveMode":7,"vertexBundelIndices":[0],"indexView":{"offset":21216,"length":2640,"count":660,"stride":4}},{"primitiveMode":7,"vertexBundelIndices":[1],"indexView":{"offset":77232,"length":6600,"count":1650,"stride":4}},{"primitiveMode":7,"vertexBundelIndices":[2],"indexView":{"offset":152184,"length":8544,"count":2136,"stride":4}},{"primitiveMode":7,"vertexBundelIndices":[3],"indexView":{"offset":254232,"length":12000,"count":3000,"stride":4}}],"vertexBundles":[{"view":{"offset":0,"length":21216,"count":442,"stride":48},"attributes":[{"name":"a_position","format":32,"isNormalized":false},{"name":"a_normal","format":32,"isNormalized":false},{"name":"a_texCoord","format":21,"isNormalized":false},{"name":"a_tangent","format":44,"isNormalized":false}]},{"view":{"offset":23856,"length":53376,"count":1112,"stride":48},"attributes":[{"name":"a_position","format":32,"isNormalized":false},{"name":"a_normal","format":32,"isNormalized":false},{"name":"a_texCoord","format":21,"isNormalized":false},{"name":"a_tangent","format":44,"isNormalized":false}]},{"view":{"offset":83832,"length":68352,"count":1424,"stride":48},"attributes":[{"name":"a_position","format":32,"isNormalized":false},{"name":"a_normal","format":32,"isNormalized":false},{"name":"a_texCoord","format":21,"isNormalized":false},{"name":"a_tangent","format":44,"isNormalized":false}]},{"view":{"offset":160728,"length":93504,"count":1948,"stride":48},"attributes":[{"name":"a_position","format":32,"isNormalized":false},{"name":"a_normal","format":32,"isNormalized":false},{"name":"a_texCoord","format":21,"isNormalized":false},{"name":"a_tangent","format":44,"isNormalized":false}]}]},"minPosition",8,[1,-0.018954146653413773,-0.09470431506633759,-0.27893388271331787],"maxPosition",8,[1,0.04094603657722473,0.1578798145055771,0.15307851135730743]]],-1],0,0,[],[],[]]
